simplex/__init__.py
simplex/magic_dictionary.py
simplex/simplex_dictionary.py
simplex_dictionary-0.0.1.dist-info/LICENSE
simplex_dictionary-0.0.1.dist-info/METADATA
simplex_dictionary-0.0.1.dist-info/WHEEL
simplex_dictionary-0.0.1.dist-info/top_level.txt
simplex_dictionary-0.0.1.dist-info/RECORD
