Metadata-Version: 2.1
Name: simplex-dictionary
Version: 0.0.1
Summary: Implementation of a simplex dictionary in python
Home-page: https://gitea.typename.fr/mikael.capelle/simplex
Author: Mikaël Capelle
Author-email: capelle.mikael@gmail.com
License: UNKNOWN
Platform: UNKNOWN
Classifier: Programming Language :: Python :: 3
Classifier: License :: OSI Approved :: MIT License
Classifier: Operating System :: OS Independent
Requires-Python: >=3.6
Provides-Extra: test
Requires-Dist: pytest ; extra == 'test'
Requires-Dist: mypy ; extra == 'test'
Requires-Dist: black ; extra == 'test'
Requires-Dist: flake8 ; extra == 'test'
Requires-Dist: flake8-black ; extra == 'test'
